LICENSE
MANIFEST.in
README.rst
pytest_wetest.py
setup.py
utl.py
pytest_wetest.egg-info/PKG-INFO
pytest_wetest.egg-info/SOURCES.txt
pytest_wetest.egg-info/dependency_links.txt
pytest_wetest.egg-info/entry_points.txt
pytest_wetest.egg-info/requires.txt
pytest_wetest.egg-info/top_level.txt