Metadata-Version: 2.1
Name: pytest-wetest
Version: 1.0.1
Summary: Welian API Automation test framework pytest plugin
Home-page: https://github.com/megachweng/pytest-wetest
Author: megachweng
Author-email: megachweng@gmail.com
Maintainer: megachweng
Maintainer-email: megachweng@gmail.com
License: MIT
Platform: UNKNOWN
Classifier: Development Status :: 4 - Beta
Classifier: Framework :: Pytest
Classifier: Intended Audience :: Developers
Classifier: Topic :: Software Development :: Testing
Classifier: Programming Language :: Python :: 3.6
Classifier: Programming Language :: Python :: 3.7
Classifier: Operating System :: OS Independent
Classifier: License :: OSI Approved :: MIT License
Requires-Python: >=3.6
